{
  "id": "introduccion/instalacion",
  "title": "Instalación",
  "description": "Requisitos previos",
  "source": "@site/docs/introduccion/instalacion.md",
  "sourceDirName": "introduccion",
  "slug": "/introduccion/instalacion",
  "permalink": "/ModaMagica/introduccion/instalacion",
  "draft": false,
  "unlisted": false,
  "tags": [],
  "version": "current",
  "sidebarPosition": 2,
  "frontMatter": {
    "id": "instalacion",
    "title": "Instalación",
    "sidebar_position": 2
  },
  "sidebar": "docs",
  "previous": {
    "title": "¿Qué es Moda Mágica?",
    "permalink": "/ModaMagica/"
  },
  "next": {
    "title": "Estructura del proyecto",
    "permalink": "/ModaMagica/introduccion/estructura"
  }
}